{
	"data": {
		"catoncounts": [{
			"index": "5",
			"pairs": {
				"16": "5.0",
				"15": "8.0",
				"14": "5.0",
				"13": "8.0"
			},
			"x": ""
		}, {
			"index": "10",
			"pairs": {
				"16": "10.0",
				"15": "9.0",
				"14": "10.0",
				"13": "9.0"
			},
			"x": ""
		}],
		"catontimes": [{
			"index": "5",
			"pairs": {
				"16": "5.00",
				"15": "3.00",
				"14": "5.00",
				"13": "3.00"
			},
			"x": ""
		}, {
			"index": "10",
			"pairs": {
				"16": "10.00",
				"15": "4.00",
				"14": "10.00",
				"13": "4.00"
			},
			"x": ""
		}],
		"index": ["13", "14", "15", "16"]
	},
	"status": "true"
}
